print_hello_hanlin/__init__.py
print_hello_hanlin/print_hello.py
print_hello_hanlin-0.0.1.dist-info/LICENSE.txt
print_hello_hanlin-0.0.1.dist-info/METADATA
print_hello_hanlin-0.0.1.dist-info/WHEEL
print_hello_hanlin-0.0.1.dist-info/top_level.txt
print_hello_hanlin-0.0.1.dist-info/RECORD
