Metadata-Version: 2.1
Name: print-hello-hanlin
Version: 0.0.1
Summary: A custom print libary
Home-page: https://github.com/HarryChen1995/print_hello.git
Author: hanlin chen
License: UNKNOWN
Platform: UNKNOWN
Requires-Python: >=3.5
License-File: LICENSE.txt
